imgal/__init__.py
imgal/imgal.cpython-311-darwin.so
pyimgal-0.2.0.dist-info/METADATA
pyimgal-0.2.0.dist-info/WHEEL
pyimgal-0.2.0.dist-info/RECORD
